pdftradoc/__init__.py
pdftradoc/extractor.py
pdftradoc-1.1.0.dist-info/licenses/LICENSE
pdftradoc-1.1.0.dist-info/METADATA
pdftradoc-1.1.0.dist-info/WHEEL
pdftradoc-1.1.0.dist-info/top_level.txt
pdftradoc-1.1.0.dist-info/RECORD
