Metadata-Version: 2.4
Name: pdftradoc
Version: 1.1.0
Summary: A Python library for translating PDF documents while preserving the original layout
Author: PdfTradoc
License: MIT
Project-URL: Homepage, https://github.com/pdftradoc/pdftradoc
Project-URL: Documentation, https://github.com/pdftradoc/pdftradoc#readme
Project-URL: Repository, https://github.com/pdftradoc/pdftradoc
Project-URL: Issues, https://github.com/pdftradoc/pdftradoc/issues
Keywords: pdf,translation,translate,document,overlay,layout,preserve,pymupdf,fitz,ocr,segmentation
Classifier: Development Status :: 4 - Beta
Classifier: Intended Audience :: Developers
Classifier: License :: OSI Approved :: MIT License
Classifier: Operating System :: OS Independent
Classifier: Programming Language :: Python :: 3
Classifier: Programming Language :: Python :: 3.8
Classifier: Programming Language :: Python :: 3.9
Classifier: Programming Language :: Python :: 3.10
Classifier: Programming Language :: Python :: 3.11
Classifier: Programming Language :: Python :: 3.12
Classifier: Topic :: Text Processing :: Linguistic
Classifier: Topic :: Multimedia :: Graphics :: Graphics Conversion
Requires-Python: >=3.8
License-File: LICENSE
Requires-Dist: PyMuPDF>=1.23.0
Requires-Dist: deep-translator>=1.11.0
Requires-Dist: Pillow>=10.0.0
Dynamic: license-file
Dynamic: requires-python
